setup.py
audion/__init__.py
audion/_version.py
audion.egg-info/PKG-INFO
audion.egg-info/SOURCES.txt
audion.egg-info/dependency_links.txt
audion.egg-info/top_level.txt