Metadata-Version: 2.1
Name: audion
Version: 0.0.0
Summary: audion
Home-page: http://github.com/serwy/audion
Author: Roger D. Serwy
Author-email: roger.serwy@gmail.com
License: UNKNOWN
Platform: UNKNOWN
Classifier: Development Status :: 2 - Pre-Alpha
Classifier: Operating System :: OS Independent
Classifier: Programming Language :: Python :: 3
